show_in_browser/__init__.py
show_in_browser/show_in_browser.py
show_in_browser-0.1.6.dist-info/LICENSE.txt
show_in_browser-0.1.6.dist-info/METADATA
show_in_browser-0.1.6.dist-info/WHEEL
show_in_browser-0.1.6.dist-info/top_level.txt
show_in_browser-0.1.6.dist-info/RECORD
