Metadata-Version: 2.1
Name: show_in_browser
Version: 0.1.6
Summary: A simple python package for rendering a Pandas DataFrames and matplotlib/plotly plots in a browser.
Home-page: https://github.com/pxr687/show_in_browser
Author: Peter Rush; Mircea-Andrei Radu
License: MIT
Classifier: Operating System :: POSIX :: Linux
Classifier: Operating System :: Microsoft :: Windows
License-File: LICENSE.txt
Requires-Dist: pandas
Requires-Dist: aspose-words
